<?xml version="1.0" encoding="utf-8" ?>
<c2layout>
    <name>2-fase</name>
    <sid>689008437642823</sid>
    <event-sheet>1-fase</event-sheet>
    <size>
        <width>1280</width>
        <height>480</height>
    </size>
    <margins>
        <horizontal>500</horizontal>
        <vertical>500</vertical>
    </margins>
    <unbounded-scrolling>0</unbounded-scrolling>
    <layers>
        <layer name="Background" sid="154060583971128">
            <initially-visible>1</initially-visible>
            <background-color>255,255,255</background-color>
            <transparent>0</transparent>
            <parallax>
                <x>1</x>
                <y>1</y>
            </parallax>
            <zoom-rate>1</zoom-rate>
            <opacity>1</opacity>
            <force-own-texture>0</force-own-texture>
            <global>0</global>
            <use-render-cells>0</use-render-cells>
            <blend-mode>0</blend-mode>
            <effect-fallback>0</effect-fallback>
            <instances>
                <instance type="bg" uid="112">
                    <properties>
                        <initial-visibility>Visible</initial-visibility>
                        <hotspot>Top-left</hotspot>
                    </properties>
                    <effect-instances>
                        <effect-instance type="Darken" />
                    </effect-instances>
                    <blend-mode>0</blend-mode>
                    <effect-fallback>0</effect-fallback>
                    <world>
                        <x>0</x>
                        <y>0</y>
                        <z>0</z>
                        <width>1280</width>
                        <height>480</height>
                        <depth>0</depth>
                        <hotspotX>0</hotspotX>
                        <hotspotY>0</hotspotY>
                        <angle>0</angle>
                        <opacity>1</opacity>
                    </world>
                </instance>
                <instance type="buraco" uid="21">
                    <properties>
                        <initial-visibility>Visible</initial-visibility>
                        <initial-animation>Default</initial-animation>
                        <initial-frame>0</initial-frame>
                        <collisions>Enabled</collisions>
                    </properties>
                    <behavior-instances>
                        <behavior-instance type="Solid">
                            <properties>
                                <initial-state>Enabled</initial-state>
                            </properties>
                        </behavior-instance>
                    </behavior-instances>
                    <blend-mode>0</blend-mode>
                    <effect-fallback>0</effect-fallback>
                    <world>
                        <x>967.5</x>
                        <y>527</y>
                        <z>0</z>
                        <width>735</width>
                        <height>84</height>
                        <depth>0</depth>
                        <hotspotX>0.5</hotspotX>
                        <hotspotY>0.5</hotspotY>
                        <angle>0</angle>
                        <opacity>1</opacity>
                    </world>
                </instance>
            </instances>
            <effects />
        </layer>
        <layer name="World" sid="206903277899405">
            <initially-visible>1</initially-visible>
            <background-color>0,255,255</background-color>
            <transparent>1</transparent>
            <parallax>
                <x>1</x>
                <y>1</y>
            </parallax>
            <zoom-rate>1</zoom-rate>
            <opacity>1</opacity>
            <force-own-texture>0</force-own-texture>
            <global>0</global>
            <use-render-cells>0</use-render-cells>
            <blend-mode>0</blend-mode>
            <effect-fallback>0</effect-fallback>
            <instances>
                <instance type="bloco" uid="116">
                    <properties>
                        <initial-visibility>Visible</initial-visibility>
                        <initial-animation>Default</initial-animation>
                        <initial-frame>0</initial-frame>
                        <collisions>Enabled</collisions>
                    </properties>
                    <behavior-instances>
                        <behavior-instance type="Solid">
                            <properties>
                                <initial-state>Enabled</initial-state>
                            </properties>
                        </behavior-instance>
                    </behavior-instances>
                    <blend-mode>0</blend-mode>
                    <effect-fallback>0</effect-fallback>
                    <world>
                        <x>1328</x>
                        <y>235</y>
                        <z>0</z>
                        <width>96</width>
                        <height>487.333831787</height>
                        <depth>0</depth>
                        <hotspotX>0.5</hotspotX>
                        <hotspotY>0.5</hotspotY>
                        <angle>0</angle>
                        <opacity>1</opacity>
                    </world>
                </instance>
                <instance type="Tilemap" uid="136">
                    <properties>
                        <initial-visibility>Visible</initial-visibility>
                        <tile-width>32</tile-width>
                        <tile-height>32</tile-height>
                        <tile-x-offset>0</tile-x-offset>
                        <tile-y-offset>0</tile-y-offset>
                        <tile-x-spacing>0</tile-x-spacing>
                        <tile-y-spacing>0</tile-y-spacing>
                        <seamless-mode>On</seamless-mode>
                    </properties>
                    <behavior-instances>
                        <behavior-instance type="Solid">
                            <properties>
                                <initial-state>Enabled</initial-state>
                            </properties>
                        </behavior-instance>
                    </behavior-instances>
                    <blend-mode>0</blend-mode>
                    <effect-fallback>0</effect-fallback>
                    <world>
                        <x>0</x>
                        <y>0</y>
                        <z>0</z>
                        <width>1280</width>
                        <height>480</height>
                        <depth>0</depth>
                        <hotspotX>0</hotspotX>
                        <hotspotY>0</hotspotY>
                        <opacity>1</opacity>
                    </world>
                    <tilemap-data>
                        <width>40</width>
                        <height>15</height>
                        <max-width>40</max-width>
                        <max-height>15</max-height>
                        <data>-1,-1,-1,-1,-1,-1,4,-1,-1,3,-1,-1,-1,41,3,-1,-1,-1,-1,-1,-1,5,-1,-1,4,-1,-1,-1,41,4,-1,-1,-1,-1,-1,-1,-1610612695,-1,-1,5,-1,-1,-1,29,4,-1,-1,-1,-1,-1,-1,-1,-1,-1,-1,-1,-1,-1,41,4,-1,-1,-1,-1,-1,-1,-1,-1,-1,-1,-1,-1,-1,41,4,-1,-1,-1,3,-1,-1,-1,-1,-1,-1,-1,-1,-1,-2147483607,4,-1,-1,-1,4,-1,-1,-1,-1,-1,-1,-1,-1,-1,-2147483619,4,-1,-1,-1,4,-1,-1,-1,-1,-1,-1,-1,-1,-1,-1,4,-1,29,3,10,1610612739,35,3,536870916,536870916,1610612739,-1,-1,-1,-1,4,-1,-1,5,-1610612732,-1610612732,-1610612732,-1610612732,-1610612732,-1610612732,-1073741820,-1,-1,-1,-1,4,-1,-1,-1,-1,4,22,-1,-1610612701,23,-1073741820,-1,-1,-1,-1,4,-1,-1,-1,-1,4,22,-1,-1,23,-1073741820,16,-1,-1,-1,4,-1,-1,-1,-1,4,-1,-1,-1,23,-1073741820,-1,-1,-1,-1,4,-1,-1,-1,-1,4,-1,-1,-1,-1,1073741829,-1,-1,-1,-1,4,-1,-1,-1,-1,5,-1,-1,-1,-1,-1,-1,-1,-1,35,4,-1,-1,-1,-1,-1610612695,-1,-1,-1,-1,-1,-1,-1,-1,-1,4,-1,-1,-1,-1,-1,-1,-1,-1,-1,-1,-1,-1,-1,-1,4,-1,-1,-1,-1,-1,-1,-1,-1,-1,-1,13,19,-1,-1,4,-1,-1,3,-1,-1,-1,-1,536870941,-1,-1,-1,4,-1,-1,4,-1,-1,4,-1,-1,-1,-1,3,-1,-1,-1,4,-1,-1,5,-1,-1,5,-1,-1,-1,-1,4,-1,-1,35,4,-1,-1,-1,-1,-1,-1,-1,-1,-1,3,10,-1,-1,-1,4,-1,536870941,-1,-1,-1,-1,-1,-1,-1,4,10,-1,-1,-1,4,1610612740,1610612740,1610612740,-1,-1,-1,-1,-1,3,-1610612726,-1610612731,-1,-1,-1,4,-1610612732,-1610612732,10,-1,-1,-1,-1,3,-1610612726,-1610612731,-1,-1,-1,-1,4,-1610612701,-1,4,-1,-1,-1,3,-1610612726,-1610612731,-1,-1,-1,-1,14,-1610612704,-1,-1,4,-1,-1,-1,4,-1610612731,-1,-1,-1,-1,25,-1,-1,-1,-1,5,-1,-1,-1,4,-1610612707,-1,-1,-1,25,-1,-1,-1,-1,-1,-1,-1,-1,-1,4,-1,-1,-1,-1,26,-1,-1,-1,-1,-1,-1,-1,-1,-1,4,-1,-1,-1,-1,4,-1,-1,-1,-1,-1,-1,-1,-1,-1,4,-1,-1,-1,-1,4,-1,-1,-1,-1,-1,-1,-1,-1,-1,4,-1,-1,-1,-1,4,-1,-1,-1,-1,-1,-1,-1,-1,-1,4,-1,-1,-1,-1,4,-1,-1,-1,-1,-1,-1,-1,-1,-1,4,-1,-1,-1,-1,5,-1,-1,-1,-1,-1,3,-1,-1,-1,4,-1,-1,-1,-1,-1,-1,-1,-1,-1,1610612771,4,-1,-1,-1,4,-1,-1,-1,-1,-1,-1,-1,-1,13,-1610612732,-1610612732,-1,-1,-1,4,-1,-1,-1,-1,-1,-1,-1,-1,-1,-1,-1,-1,-1,-1,4,22,-1,-1,-1,-1,-1,-1,-1,-1,-1,-1,-1,-1,-1,4,22,-1,-1,-1,-1,-1,-1,-1,-1,-1,-1,-1,-1,-1,4,22,-1,-1,-1,-1,-1,-1,-1,-1,-1,-1</data>
                    </tilemap-data>
                </instance>
            </instances>
            <effects />
        </layer>
        <layer name="Objetos" sid="415960099905596">
            <initially-visible>1</initially-visible>
            <background-color>255,255,255</background-color>
            <transparent>1</transparent>
            <parallax>
                <x>1</x>
                <y>1</y>
            </parallax>
            <zoom-rate>1</zoom-rate>
            <opacity>1</opacity>
            <force-own-texture>0</force-own-texture>
            <global>0</global>
            <use-render-cells>0</use-render-cells>
            <blend-mode>0</blend-mode>
            <effect-fallback>0</effect-fallback>
            <instances>
                <instance type="jogador" uid="137">
                    <properties>
                        <initial-visibility>Visible</initial-visibility>
                        <initial-animation>Default</initial-animation>
                        <initial-frame>0</initial-frame>
                        <collisions>Enabled</collisions>
                    </properties>
                    <instance-variables>
                        <CORRER>0</CORRER>
                        <VIDA>200</VIDA>
                        <POR_VIDA>0</POR_VIDA>
                    </instance-variables>
                    <behavior-instances>
                        <behavior-instance type="Solid">
                            <properties>
                                <initial-state>Enabled</initial-state>
                            </properties>
                        </behavior-instance>
                        <behavior-instance type="Platform">
                            <properties>
                                <max-speed>150</max-speed>
                                <acceleration>1500</acceleration>
                                <deceleration>1500</deceleration>
                                <jump-strength>650</jump-strength>
                                <gravity>1500</gravity>
                                <max-fall-speed>1000</max-fall-speed>
                                <double-jump>Disabled</double-jump>
                                <jump-sustain>0</jump-sustain>
                                <default-controls>No</default-controls>
                                <initial-state>Enabled</initial-state>
                            </properties>
                        </behavior-instance>
                        <behavior-instance type="ScrollTo">
                            <properties>
                                <initial-state>Enabled</initial-state>
                            </properties>
                        </behavior-instance>
                    </behavior-instances>
                    <blend-mode>0</blend-mode>
                    <effect-fallback>0</effect-fallback>
                    <world>
                        <x>51</x>
                        <y>444</y>
                        <z>0</z>
                        <width>30</width>
                        <height>29</height>
                        <depth>0</depth>
                        <hotspotX>0.538461566</hotspotX>
                        <hotspotY>1.039999962</hotspotY>
                        <angle>0</angle>
                        <opacity>1</opacity>
                    </world>
                </instance>
                <instance type="pes" uid="142">
                    <properties>
                        <initial-visibility>Invisible</initial-visibility>
                        <initial-animation>Default</initial-animation>
                        <initial-frame>0</initial-frame>
                        <collisions>Enabled</collisions>
                    </properties>
                    <behavior-instances>
                        <behavior-instance type="Pin" />
                    </behavior-instances>
                    <blend-mode>0</blend-mode>
                    <effect-fallback>0</effect-fallback>
                    <world>
                        <x>48</x>
                        <y>443</y>
                        <z>0</z>
                        <width>36.581680298</width>
                        <height>8</height>
                        <depth>0</depth>
                        <hotspotX>0.5</hotspotX>
                        <hotspotY>0.5</hotspotY>
                        <angle>0</angle>
                        <opacity>1</opacity>
                    </world>
                </instance>
                <instance type="bloco" uid="114">
                    <properties>
                        <initial-visibility>Visible</initial-visibility>
                        <initial-animation>Default</initial-animation>
                        <initial-frame>0</initial-frame>
                        <collisions>Enabled</collisions>
                    </properties>
                    <behavior-instances>
                        <behavior-instance type="Solid">
                            <properties>
                                <initial-state>Enabled</initial-state>
                            </properties>
                        </behavior-instance>
                    </behavior-instances>
                    <blend-mode>0</blend-mode>
                    <effect-fallback>0</effect-fallback>
                    <world>
                        <x>-49</x>
                        <y>237</y>
                        <z>0</z>
                        <width>96</width>
                        <height>480</height>
                        <depth>0</depth>
                        <hotspotX>0.5</hotspotX>
                        <hotspotY>0.5</hotspotY>
                        <angle>0</angle>
                        <opacity>1</opacity>
                    </world>
                </instance>
                <instance type="bloco" uid="123">
                    <properties>
                        <initial-visibility>Visible</initial-visibility>
                        <initial-animation>Default</initial-animation>
                        <initial-frame>0</initial-frame>
                        <collisions>Enabled</collisions>
                    </properties>
                    <behavior-instances>
                        <behavior-instance type="Solid">
                            <properties>
                                <initial-state>Enabled</initial-state>
                            </properties>
                        </behavior-instance>
                    </behavior-instances>
                    <blend-mode>0</blend-mode>
                    <effect-fallback>0</effect-fallback>
                    <world>
                        <x>292.749023438</x>
                        <y>509</y>
                        <z>0</z>
                        <width>590</width>
                        <height>57</height>
                        <depth>0</depth>
                        <hotspotX>0.5</hotspotX>
                        <hotspotY>0.5</hotspotY>
                        <angle>0</angle>
                        <opacity>1</opacity>
                    </world>
                </instance>
                <instance type="presente" uid="22">
                    <properties>
                        <initial-visibility>Visible</initial-visibility>
                        <initial-animation>Default</initial-animation>
                        <initial-frame>0</initial-frame>
                        <collisions>Enabled</collisions>
                    </properties>
                    <instance-variables>
                        <valor>0</valor>
                    </instance-variables>
                    <blend-mode>0</blend-mode>
                    <effect-fallback>0</effect-fallback>
                    <world>
                        <x>167</x>
                        <y>241</y>
                        <z>0</z>
                        <width>33.148788452</width>
                        <height>33.148788452</height>
                        <depth>0</depth>
                        <hotspotX>0.5</hotspotX>
                        <hotspotY>0.5</hotspotY>
                        <angle>0</angle>
                        <opacity>1</opacity>
                    </world>
                </instance>
                <instance type="presente" uid="24">
                    <properties>
                        <initial-visibility>Visible</initial-visibility>
                        <initial-animation>Default</initial-animation>
                        <initial-frame>0</initial-frame>
                        <collisions>Enabled</collisions>
                    </properties>
                    <instance-variables>
                        <valor>0</valor>
                    </instance-variables>
                    <blend-mode>0</blend-mode>
                    <effect-fallback>0</effect-fallback>
                    <world>
                        <x>957</x>
                        <y>202</y>
                        <z>0</z>
                        <width>33.148788452</width>
                        <height>33.148788452</height>
                        <depth>0</depth>
                        <hotspotX>0.5</hotspotX>
                        <hotspotY>0.5</hotspotY>
                        <angle>0</angle>
                        <opacity>1</opacity>
                    </world>
                </instance>
                <instance type="presente" uid="25">
                    <properties>
                        <initial-visibility>Visible</initial-visibility>
                        <initial-animation>Default</initial-animation>
                        <initial-frame>0</initial-frame>
                        <collisions>Enabled</collisions>
                    </properties>
                    <instance-variables>
                        <valor>0</valor>
                    </instance-variables>
                    <blend-mode>0</blend-mode>
                    <effect-fallback>0</effect-fallback>
                    <world>
                        <x>1219</x>
                        <y>63</y>
                        <z>0</z>
                        <width>33.148788452</width>
                        <height>33.148788452</height>
                        <depth>0</depth>
                        <hotspotX>0.5</hotspotX>
                        <hotspotY>0.5</hotspotY>
                        <angle>0</angle>
                        <opacity>1</opacity>
                    </world>
                </instance>
                <instance type="alavanca" uid="81">
                    <properties>
                        <initial-visibility>Visible</initial-visibility>
                        <initial-animation>Default</initial-animation>
                        <initial-frame>0</initial-frame>
                        <collisions>Enabled</collisions>
                    </properties>
                    <behavior-instances>
                        <behavior-instance type="Solid">
                            <properties>
                                <initial-state>Enabled</initial-state>
                            </properties>
                        </behavior-instance>
                    </behavior-instances>
                    <blend-mode>0</blend-mode>
                    <effect-fallback>0</effect-fallback>
                    <world>
                        <x>347</x>
                        <y>268</y>
                        <z>0</z>
                        <width>31.399324417</width>
                        <height>30.143352509</height>
                        <depth>0</depth>
                        <hotspotX>0.600000024</hotspotX>
                        <hotspotY>0.291666657</hotspotY>
                        <angle>0</angle>
                        <opacity>1</opacity>
                    </world>
                </instance>
                <instance type="coracao" uid="62">
                    <properties>
                        <initial-visibility>Visible</initial-visibility>
                        <initial-animation>Default</initial-animation>
                        <initial-frame>0</initial-frame>
                        <collisions>Enabled</collisions>
                    </properties>
                    <blend-mode>0</blend-mode>
                    <effect-fallback>0</effect-fallback>
                    <world>
                        <x>67</x>
                        <y>122</y>
                        <z>0</z>
                        <width>35.316379547</width>
                        <height>35.316379547</height>
                        <depth>0</depth>
                        <hotspotX>0.5</hotspotX>
                        <hotspotY>0.5</hotspotY>
                        <angle>0</angle>
                        <opacity>1</opacity>
                    </world>
                </instance>
                <instance type="inimigo" uid="85">
                    <properties>
                        <initial-visibility>Visible</initial-visibility>
                        <initial-animation>Default</initial-animation>
                        <initial-frame>0</initial-frame>
                        <collisions>Enabled</collisions>
                    </properties>
                    <instance-variables>
                        <direcao>direita</direcao>
                    </instance-variables>
                    <behavior-instances>
                        <behavior-instance type="Solid">
                            <properties>
                                <initial-state>Enabled</initial-state>
                            </properties>
                        </behavior-instance>
                        <behavior-instance type="Platform">
                            <properties>
                                <max-speed>100</max-speed>
                                <acceleration>1500</acceleration>
                                <deceleration>1500</deceleration>
                                <jump-strength>650</jump-strength>
                                <gravity>1500</gravity>
                                <max-fall-speed>1000</max-fall-speed>
                                <double-jump>Disabled</double-jump>
                                <jump-sustain>0</jump-sustain>
                                <default-controls>No</default-controls>
                                <initial-state>Enabled</initial-state>
                            </properties>
                        </behavior-instance>
                    </behavior-instances>
                    <blend-mode>0</blend-mode>
                    <effect-fallback>0</effect-fallback>
                    <world>
                        <x>779.527648926</x>
                        <y>329.703613281</y>
                        <z>0</z>
                        <width>51.877422333</width>
                        <height>52.914970398</height>
                        <depth>0</depth>
                        <hotspotX>0.460000008</hotspotX>
                        <hotspotY>0.568627477</hotspotY>
                        <angle>0</angle>
                        <opacity>1</opacity>
                    </world>
                </instance>
                <instance type="inimigo2" uid="86">
                    <properties>
                        <initial-visibility>Visible</initial-visibility>
                        <initial-animation>Default</initial-animation>
                        <initial-frame>0</initial-frame>
                        <collisions>Enabled</collisions>
                    </properties>
                    <behavior-instances>
                        <behavior-instance type="Solid">
                            <properties>
                                <initial-state>Enabled</initial-state>
                            </properties>
                        </behavior-instance>
                        <behavior-instance type="Platform">
                            <properties>
                                <max-speed>330</max-speed>
                                <acceleration>1500</acceleration>
                                <deceleration>1500</deceleration>
                                <jump-strength>650</jump-strength>
                                <gravity>1500</gravity>
                                <max-fall-speed>1000</max-fall-speed>
                                <double-jump>Disabled</double-jump>
                                <jump-sustain>0</jump-sustain>
                                <default-controls>No</default-controls>
                                <initial-state>Enabled</initial-state>
                            </properties>
                        </behavior-instance>
                    </behavior-instances>
                    <blend-mode>0</blend-mode>
                    <effect-fallback>0</effect-fallback>
                    <world>
                        <x>1086.937866211</x>
                        <y>47.379180908</y>
                        <z>0</z>
                        <width>79.204925537</width>
                        <height>80.789024353</height>
                        <depth>0</depth>
                        <hotspotX>0.159999996</hotspotX>
                        <hotspotY>0.764705896</hotspotY>
                        <angle>0</angle>
                        <opacity>1</opacity>
                    </world>
                </instance>
                <instance type="presente" uid="87">
                    <properties>
                        <initial-visibility>Visible</initial-visibility>
                        <initial-animation>Default</initial-animation>
                        <initial-frame>0</initial-frame>
                        <collisions>Enabled</collisions>
                    </properties>
                    <instance-variables>
                        <valor>0</valor>
                    </instance-variables>
                    <blend-mode>0</blend-mode>
                    <effect-fallback>0</effect-fallback>
                    <world>
                        <x>393</x>
                        <y>74</y>
                        <z>0</z>
                        <width>33.148788452</width>
                        <height>33.148788452</height>
                        <depth>0</depth>
                        <hotspotX>0.5</hotspotX>
                        <hotspotY>0.5</hotspotY>
                        <angle>0</angle>
                        <opacity>1</opacity>
                    </world>
                </instance>
                <instance type="presente" uid="88">
                    <properties>
                        <initial-visibility>Visible</initial-visibility>
                        <initial-animation>Default</initial-animation>
                        <initial-frame>0</initial-frame>
                        <collisions>Enabled</collisions>
                    </properties>
                    <instance-variables>
                        <valor>0</valor>
                    </instance-variables>
                    <blend-mode>0</blend-mode>
                    <effect-fallback>0</effect-fallback>
                    <world>
                        <x>1252</x>
                        <y>333</y>
                        <z>0</z>
                        <width>33.148788452</width>
                        <height>33.148788452</height>
                        <depth>0</depth>
                        <hotspotX>0.5</hotspotX>
                        <hotspotY>0.5</hotspotY>
                        <angle>0</angle>
                        <opacity>1</opacity>
                    </world>
                </instance>
                <instance type="presente" uid="89">
                    <properties>
                        <initial-visibility>Visible</initial-visibility>
                        <initial-animation>Default</initial-animation>
                        <initial-frame>0</initial-frame>
                        <collisions>Enabled</collisions>
                    </properties>
                    <instance-variables>
                        <valor>0</valor>
                    </instance-variables>
                    <blend-mode>0</blend-mode>
                    <effect-fallback>0</effect-fallback>
                    <world>
                        <x>983</x>
                        <y>349</y>
                        <z>0</z>
                        <width>33.148788452</width>
                        <height>33.148788452</height>
                        <depth>0</depth>
                        <hotspotX>0.5</hotspotX>
                        <hotspotY>0.5</hotspotY>
                        <angle>0</angle>
                        <opacity>1</opacity>
                    </world>
                </instance>
                <instance type="parede2" uid="90">
                    <properties>
                        <initial-visibility>Visible</initial-visibility>
                        <initial-animation>Default</initial-animation>
                        <initial-frame>0</initial-frame>
                        <collisions>Enabled</collisions>
                    </properties>
                    <behavior-instances>
                        <behavior-instance type="Solid">
                            <properties>
                                <initial-state>Enabled</initial-state>
                            </properties>
                        </behavior-instance>
                    </behavior-instances>
                    <blend-mode>0</blend-mode>
                    <effect-fallback>0</effect-fallback>
                    <world>
                        <x>835</x>
                        <y>369</y>
                        <z>0</z>
                        <width>280.043762207</width>
                        <height>11.548195839</height>
                        <depth>0</depth>
                        <hotspotX>0</hotspotX>
                        <hotspotY>0</hotspotY>
                        <angle>0</angle>
                        <opacity>1</opacity>
                    </world>
                </instance>
                <instance type="portal2" uid="91">
                    <properties>
                        <initial-visibility>Visible</initial-visibility>
                        <initial-animation>Default</initial-animation>
                        <initial-frame>0</initial-frame>
                        <collisions>Enabled</collisions>
                    </properties>
                    <behavior-instances>
                        <behavior-instance type="Solid">
                            <properties>
                                <initial-state>Enabled</initial-state>
                            </properties>
                        </behavior-instance>
                    </behavior-instances>
                    <blend-mode>0</blend-mode>
                    <effect-fallback>0</effect-fallback>
                    <world>
                        <x>785</x>
                        <y>417</y>
                        <z>0</z>
                        <width>40</width>
                        <height>66</height>
                        <depth>0</depth>
                        <hotspotX>0.550000012</hotspotX>
                        <hotspotY>0.5</hotspotY>
                        <angle>0</angle>
                        <opacity>1</opacity>
                    </world>
                </instance>
                <instance type="pontecai" uid="92">
                    <properties>
                        <initial-visibility>Visible</initial-visibility>
                        <initial-animation>Default</initial-animation>
                        <initial-frame>0</initial-frame>
                        <collisions>Enabled</collisions>
                    </properties>
                    <behavior-instances>
                        <behavior-instance type="Solid">
                            <properties>
                                <initial-state>Enabled</initial-state>
                            </properties>
                        </behavior-instance>
                        <behavior-instance type="Bullet">
                            <properties>
                                <speed>0</speed>
                                <acceleration>0</acceleration>
                                <gravity>300</gravity>
                                <bounce-off-solids>No</bounce-off-solids>
                                <set-angle>No</set-angle>
                                <initial-state>Disabled</initial-state>
                            </properties>
                        </behavior-instance>
                    </behavior-instances>
                    <blend-mode>0</blend-mode>
                    <effect-fallback>0</effect-fallback>
                    <world>
                        <x>877</x>
                        <y>464</y>
                        <z>0</z>
                        <width>32</width>
                        <height>32</height>
                        <depth>0</depth>
                        <hotspotX>0.433333337</hotspotX>
                        <hotspotY>0.483870953</hotspotY>
                        <angle>0</angle>
                        <opacity>1</opacity>
                    </world>
                </instance>
                <instance type="pontecai" uid="93">
                    <properties>
                        <initial-visibility>Visible</initial-visibility>
                        <initial-animation>Default</initial-animation>
                        <initial-frame>0</initial-frame>
                        <collisions>Enabled</collisions>
                    </properties>
                    <behavior-instances>
                        <behavior-instance type="Solid">
                            <properties>
                                <initial-state>Enabled</initial-state>
                            </properties>
                        </behavior-instance>
                        <behavior-instance type="Bullet">
                            <properties>
                                <speed>0</speed>
                                <acceleration>0</acceleration>
                                <gravity>300</gravity>
                                <bounce-off-solids>No</bounce-off-solids>
                                <set-angle>No</set-angle>
                                <initial-state>Disabled</initial-state>
                            </properties>
                        </behavior-instance>
                    </behavior-instances>
                    <blend-mode>0</blend-mode>
                    <effect-fallback>0</effect-fallback>
                    <world>
                        <x>909.13861084</x>
                        <y>464</y>
                        <z>0</z>
                        <width>32</width>
                        <height>32</height>
                        <depth>0</depth>
                        <hotspotX>0.433333337</hotspotX>
                        <hotspotY>0.483870953</hotspotY>
                        <angle>0</angle>
                        <opacity>1</opacity>
                    </world>
                </instance>
                <instance type="pontecai" uid="94">
                    <properties>
                        <initial-visibility>Visible</initial-visibility>
                        <initial-animation>Default</initial-animation>
                        <initial-frame>0</initial-frame>
                        <collisions>Enabled</collisions>
                    </properties>
                    <behavior-instances>
                        <behavior-instance type="Solid">
                            <properties>
                                <initial-state>Enabled</initial-state>
                            </properties>
                        </behavior-instance>
                        <behavior-instance type="Bullet">
                            <properties>
                                <speed>0</speed>
                                <acceleration>0</acceleration>
                                <gravity>300</gravity>
                                <bounce-off-solids>No</bounce-off-solids>
                                <set-angle>No</set-angle>
                                <initial-state>Disabled</initial-state>
                            </properties>
                        </behavior-instance>
                    </behavior-instances>
                    <blend-mode>0</blend-mode>
                    <effect-fallback>0</effect-fallback>
                    <world>
                        <x>940.945983887</x>
                        <y>464</y>
                        <z>0</z>
                        <width>32</width>
                        <height>32</height>
                        <depth>0</depth>
                        <hotspotX>0.433333337</hotspotX>
                        <hotspotY>0.483870953</hotspotY>
                        <angle>0</angle>
                        <opacity>1</opacity>
                    </world>
                </instance>
                <instance type="pontecai" uid="95">
                    <properties>
                        <initial-visibility>Visible</initial-visibility>
                        <initial-animation>Default</initial-animation>
                        <initial-frame>0</initial-frame>
                        <collisions>Enabled</collisions>
                    </properties>
                    <behavior-instances>
                        <behavior-instance type="Solid">
                            <properties>
                                <initial-state>Enabled</initial-state>
                            </properties>
                        </behavior-instance>
                        <behavior-instance type="Bullet">
                            <properties>
                                <speed>0</speed>
                                <acceleration>0</acceleration>
                                <gravity>300</gravity>
                                <bounce-off-solids>No</bounce-off-solids>
                                <set-angle>No</set-angle>
                                <initial-state>Disabled</initial-state>
                            </properties>
                        </behavior-instance>
                    </behavior-instances>
                    <blend-mode>0</blend-mode>
                    <effect-fallback>0</effect-fallback>
                    <world>
                        <x>973.416015625</x>
                        <y>464</y>
                        <z>0</z>
                        <width>32</width>
                        <height>32</height>
                        <depth>0</depth>
                        <hotspotX>0.433333337</hotspotX>
                        <hotspotY>0.483870953</hotspotY>
                        <angle>0</angle>
                        <opacity>1</opacity>
                    </world>
                </instance>
                <instance type="pontecai" uid="96">
                    <properties>
                        <initial-visibility>Visible</initial-visibility>
                        <initial-animation>Default</initial-animation>
                        <initial-frame>0</initial-frame>
                        <collisions>Enabled</collisions>
                    </properties>
                    <behavior-instances>
                        <behavior-instance type="Solid">
                            <properties>
                                <initial-state>Enabled</initial-state>
                            </properties>
                        </behavior-instance>
                        <behavior-instance type="Bullet">
                            <properties>
                                <speed>0</speed>
                                <acceleration>0</acceleration>
                                <gravity>300</gravity>
                                <bounce-off-solids>No</bounce-off-solids>
                                <set-angle>No</set-angle>
                                <initial-state>Disabled</initial-state>
                            </properties>
                        </behavior-instance>
                    </behavior-instances>
                    <blend-mode>0</blend-mode>
                    <effect-fallback>0</effect-fallback>
                    <world>
                        <x>1005.546020508</x>
                        <y>464</y>
                        <z>0</z>
                        <width>32</width>
                        <height>32</height>
                        <depth>0</depth>
                        <hotspotX>0.433333337</hotspotX>
                        <hotspotY>0.483870953</hotspotY>
                        <angle>0</angle>
                        <opacity>1</opacity>
                    </world>
                </instance>
                <instance type="pontecai" uid="98">
                    <properties>
                        <initial-visibility>Visible</initial-visibility>
                        <initial-animation>Default</initial-animation>
                        <initial-frame>0</initial-frame>
                        <collisions>Enabled</collisions>
                    </properties>
                    <behavior-instances>
                        <behavior-instance type="Solid">
                            <properties>
                                <initial-state>Enabled</initial-state>
                            </properties>
                        </behavior-instance>
                        <behavior-instance type="Bullet">
                            <properties>
                                <speed>0</speed>
                                <acceleration>0</acceleration>
                                <gravity>300</gravity>
                                <bounce-off-solids>No</bounce-off-solids>
                                <set-angle>No</set-angle>
                                <initial-state>Disabled</initial-state>
                            </properties>
                        </behavior-instance>
                    </behavior-instances>
                    <blend-mode>0</blend-mode>
                    <effect-fallback>0</effect-fallback>
                    <world>
                        <x>1037.702026367</x>
                        <y>464</y>
                        <z>0</z>
                        <width>32</width>
                        <height>32</height>
                        <depth>0</depth>
                        <hotspotX>0.433333337</hotspotX>
                        <hotspotY>0.483870953</hotspotY>
                        <angle>0</angle>
                        <opacity>1</opacity>
                    </world>
                </instance>
                <instance type="espinho" uid="101">
                    <properties>
                        <initial-visibility>Invisible</initial-visibility>
                        <initial-animation>Default</initial-animation>
                        <initial-frame>0</initial-frame>
                        <collisions>Enabled</collisions>
                    </properties>
                    <behavior-instances>
                        <behavior-instance type="Solid">
                            <properties>
                                <initial-state>Enabled</initial-state>
                            </properties>
                        </behavior-instance>
                    </behavior-instances>
                    <blend-mode>0</blend-mode>
                    <effect-fallback>0</effect-fallback>
                    <world>
                        <x>369</x>
                        <y>335</y>
                        <z>0</z>
                        <width>37</width>
                        <height>32</height>
                        <depth>0</depth>
                        <hotspotX>0.5</hotspotX>
                        <hotspotY>0.5</hotspotY>
                        <angle>0</angle>
                        <opacity>1</opacity>
                    </world>
                </instance>
                <instance type="espinho" uid="104">
                    <properties>
                        <initial-visibility>Invisible</initial-visibility>
                        <initial-animation>Default</initial-animation>
                        <initial-frame>0</initial-frame>
                        <collisions>Enabled</collisions>
                    </properties>
                    <behavior-instances>
                        <behavior-instance type="Solid">
                            <properties>
                                <initial-state>Enabled</initial-state>
                            </properties>
                        </behavior-instance>
                    </behavior-instances>
                    <blend-mode>0</blend-mode>
                    <effect-fallback>0</effect-fallback>
                    <world>
                        <x>353.5</x>
                        <y>168.5</y>
                        <z>0</z>
                        <width>60</width>
                        <height>15</height>
                        <depth>0</depth>
                        <hotspotX>0.5</hotspotX>
                        <hotspotY>0.5</hotspotY>
                        <angle>0</angle>
                        <opacity>1</opacity>
                    </world>
                </instance>
                <instance type="espinho" uid="105">
                    <properties>
                        <initial-visibility>Invisible</initial-visibility>
                        <initial-animation>Default</initial-animation>
                        <initial-frame>0</initial-frame>
                        <collisions>Enabled</collisions>
                    </properties>
                    <behavior-instances>
                        <behavior-instance type="Solid">
                            <properties>
                                <initial-state>Enabled</initial-state>
                            </properties>
                        </behavior-instance>
                    </behavior-instances>
                    <blend-mode>0</blend-mode>
                    <effect-fallback>0</effect-fallback>
                    <world>
                        <x>1229.856201172</x>
                        <y>136.19744873</y>
                        <z>0</z>
                        <width>96.712280273</width>
                        <height>12.394882202</height>
                        <depth>0</depth>
                        <hotspotX>0.5</hotspotX>
                        <hotspotY>0.5</hotspotY>
                        <angle>0</angle>
                        <opacity>1</opacity>
                    </world>
                </instance>
            </instances>
            <effects />
        </layer>
        <layer name="HUD" sid="555307430283952">
            <initially-visible>1</initially-visible>
            <background-color>255,255,255</background-color>
            <transparent>1</transparent>
            <parallax>
                <x>0</x>
                <y>0</y>
            </parallax>
            <zoom-rate>1</zoom-rate>
            <opacity>1</opacity>
            <force-own-texture>0</force-own-texture>
            <global>0</global>
            <use-render-cells>0</use-render-cells>
            <blend-mode>0</blend-mode>
            <effect-fallback>0</effect-fallback>
            <instances>
                <instance type="barra" uid="146">
                    <properties>
                        <initial-visibility>Visible</initial-visibility>
                        <initial-animation>Default</initial-animation>
                        <initial-frame>0</initial-frame>
                        <collisions>Enabled</collisions>
                    </properties>
                    <instance-variables>
                        <vidaMaxima>100</vidaMaxima>
                        <vida>100</vida>
                    </instance-variables>
                    <blend-mode>0</blend-mode>
                    <effect-fallback>0</effect-fallback>
                    <world>
                        <x>21.337272644</x>
                        <y>26.530780792</y>
                        <z>0</z>
                        <width>128.093444824</width>
                        <height>7.273741245</height>
                        <depth>0</depth>
                        <hotspotX>-0.003225806</hotspotX>
                        <hotspotY>0.578947365</hotspotY>
                        <angle>0</angle>
                        <opacity>1</opacity>
                    </world>
                </instance>
                <instance type="frame" uid="147">
                    <properties>
                        <initial-visibility>Visible</initial-visibility>
                        <initial-animation>Default</initial-animation>
                        <initial-frame>0</initial-frame>
                        <collisions>Enabled</collisions>
                    </properties>
                    <blend-mode>0</blend-mode>
                    <effect-fallback>0</effect-fallback>
                    <world>
                        <x>21.715110779</x>
                        <y>25.627895355</y>
                        <z>0</z>
                        <width>142.5025177</width>
                        <height>25.19609642</height>
                        <depth>0</depth>
                        <hotspotX>0.052173913</hotspotX>
                        <hotspotY>0.459016383</hotspotY>
                        <angle>0</angle>
                        <opacity>1</opacity>
                    </world>
                </instance>
                <instance type="subbarra" uid="148">
                    <properties>
                        <initial-visibility>Visible</initial-visibility>
                        <initial-animation>Default</initial-animation>
                        <initial-frame>0</initial-frame>
                        <collisions>Enabled</collisions>
                    </properties>
                    <blend-mode>0</blend-mode>
                    <effect-fallback>0</effect-fallback>
                    <world>
                        <x>20.918815613</x>
                        <y>25.424930573</y>
                        <z>0</z>
                        <width>129.332992554</width>
                        <height>8.038999557</height>
                        <depth>0</depth>
                        <hotspotX>0.003205128</hotspotX>
                        <hotspotY>0.476190478</hotspotY>
                        <angle>0</angle>
                        <opacity>1</opacity>
                    </world>
                </instance>
                <instance type="explosao" uid="149">
                    <properties>
                        <initial-visibility>Visible</initial-visibility>
                        <initial-animation>Default</initial-animation>
                        <initial-frame>0</initial-frame>
                        <collisions>Enabled</collisions>
                    </properties>
                    <behavior-instances>
                        <behavior-instance type="Fade">
                            <properties>
                                <active-at-start>Yes</active-at-start>
                                <fade-in-time>0</fade-in-time>
                                <wait-time>0</wait-time>
                                <fade-out-time>1</fade-out-time>
                                <destroy>After fade out</destroy>
                            </properties>
                        </behavior-instance>
                    </behavior-instances>
                    <blend-mode>0</blend-mode>
                    <effect-fallback>0</effect-fallback>
                    <world>
                        <x>139.613922119</x>
                        <y>-31.83770752</y>
                        <z>0</z>
                        <width>20.027170181</width>
                        <height>20.027170181</height>
                        <depth>0</depth>
                        <hotspotX>0.5</hotspotX>
                        <hotspotY>0.5</hotspotY>
                        <angle>0</angle>
                        <opacity>1</opacity>
                    </world>
                </instance>
                <instance type="score" uid="150">
                    <properties>
                        <text>0</text>
                        <initial-visibility>Visible</initial-visibility>
                        <font>Arial,-16</font>
                        <color>255,255,255</color>
                        <horizontal-alignment>Left</horizontal-alignment>
                        <vertical-alignment>Top</vertical-alignment>
                        <hotspot>Top-left</hotspot>
                        <wrapping>Word</wrapping>
                        <line-height>0</line-height>
                    </properties>
                    <blend-mode>0</blend-mode>
                    <effect-fallback>0</effect-fallback>
                    <world>
                        <x>167.120742798</x>
                        <y>16.947967529</y>
                        <z>0</z>
                        <width>43.333526611</width>
                        <height>30.833084106</height>
                        <depth>0</depth>
                        <hotspotX>0</hotspotX>
                        <hotspotY>0</hotspotY>
                        <angle>0</angle>
                        <opacity>1</opacity>
                    </world>
                </instance>
            </instances>
            <effects />
        </layer>
    </layers>
    <nonworld-instances />
    <effects />
</c2layout>
